lmsstat/__init__.py
lmsstat/plot/__init__.py
lmsstat/plot/_plots.py
lmsstat/plot/_utils.py
lmsstat/stat/__init__.py
lmsstat/stat/_allstat.py
lmsstat/stat/_posthoc.py
lmsstat/stat/_tests.py
lmsstat/stat/_utils.py
lmsstat-0.1.0.dist-info/licenses/LICENSE
lmsstat-0.1.0.dist-info/WHEEL
lmsstat-0.1.0.dist-info/METADATA
lmsstat-0.1.0.dist-info/RECORD
