Metadata-Version: 2.4
Name: lmsstat
Version: 0.1.0
Summary: LMSstat: Automation of statistical tests with an identical data input
Author-email: Daehwan Kim <kdh5358@snu.ac.kr>
Requires-Python: >=3.10
Classifier: Programming Language :: Python :: 3
Classifier: License :: OSI Approved :: MIT License
Classifier: Operating System :: OS Independent
License-File: LICENSE
Requires-Dist: ipykernel
Requires-Dist: numpy >= 2.0.0
Requires-Dist: pandas >= 2.0.0
Requires-Dist: scipy >= 1.11.0
Requires-Dist: statsmodels >= 0.14.2
Requires-Dist: scikit-learn >= 1.0
Requires-Dist: pingouin >= 0.5.4
Requires-Dist: plotnine >= 0.12.0
Project-URL: Source, https://github.com/SNUFML/LMSstat_python
